{
  "updated_at": "2026-06-01 11:14:46 UTC",
  "prices": [
    {
      "code": "gold",
      "name": "黄金 Gold",
      "price_usd": 4503.98,
      "unit": "USD/盎司 oz"
    },
    {
      "code": "silver",
      "name": "白银 Silver",
      "price_usd": 75.69,
      "unit": "USD/盎司 oz"
    },
    {
      "code": "platinum",
      "name": "铂 Platinum",
      "price_usd": 1940.73,
      "unit": "USD/盎司 oz"
    },
    {
      "code": "palladium",
      "name": "钯 Palladium",
      "price_usd": 1355.29,
      "unit": "USD/盎司 oz"
    },
    {
      "code": "copper",
      "name": "铜 Copper",
      "price_usd": 0.45,
      "unit": "USD/吨 mt"
    },
    {
      "code": "aluminum",
      "name": "铝 Aluminum",
      "price_usd": 0.11,
      "unit": "USD/吨 mt"
    },
    {
      "code": "nickel",
      "name": "镍 Nickel",
      "price_usd": 0.6,
      "unit": "USD/吨 mt"
    },
    {
      "code": "zinc",
      "name": "锌 Zinc",
      "price_usd": 0.11,
      "unit": "USD/吨 mt"
    },
    {
      "code": "lead",
      "name": "铅 Lead",
      "price_usd": 0.06,
      "unit": "USD/吨 mt"
    },
    {
      "code": "lme_zinc",
      "name": "LME锌 Zinc 3M",
      "price_usd": 0.11,
      "unit": "USD/吨 mt"
    },
    {
      "code": "lme_nickel",
      "name": "LME镍 Nickel 3M",
      "price_usd": 0.59,
      "unit": "USD/吨 mt"
    },
    {
      "code": "lme_copper",
      "name": "LME铜 Copper 3M",
      "price_usd": 0.42,
      "unit": "USD/吨 mt"
    }
  ],
  "news": [
    {
      "title": "RBI MPC meet: Central bank likely to maintain status quo on rates, adopt cautious approach amid West Asia crisis",
      "source": "The Times of India",
      "url": "https://economictimes.indiatimes.com/news/economy/policy/rbi-set-to-keep-rates-steady-amid-west-asia-crisis-experts-predict-cautious-economic-outlook/articleshow/131421956.cms",
      "published": "2026-05-31T11:05:36Z",
      "description": "Experts anticipate the Reserve Bank of India will maintain its key policy rate at 5.25 percent this week. The central bank is expected to adopt a cautious approach, considering potential inflation hea"
    },
    {
      "title": "RBI likely to maintain status quo on rates, adopt cautious approach amid West Asia crisis",
      "source": "BusinessLine",
      "url": "https://www.thehindubusinessline.com/money-and-banking/rbi-likely-to-maintain-status-quo-on-rates-adopt-cautious-approach-amid-west-asia-crisis/article71044397.ece",
      "published": "2026-05-31T11:03:59Z",
      "description": "The Reserve Bank of India is expected to leave the key policy rate unchanged at 5.25 per cent this week and adopt a cautious stance that factors in the possible headwinds to inflation and growth traje"
    },
    {
      "title": "India-US trade negotiators to begin four-day talks on June 1",
      "source": "The Times of India",
      "url": "https://economictimes.indiatimes.com/news/economy/foreign-trade/india-us-trade-negotiators-to-begin-four-day-talks-on-june-1/articleshow/131421376.cms",
      "published": "2026-05-31T09:56:27Z",
      "description": "India and the US are holding crucial trade talks in New Delhi. Chief negotiators will finalize details of an interim trade agreement. This pact aims to boost market access and facilitate trade. Both n"
    },
    {
      "title": "India, US chief negotiators to hold four-day trade talks from June 1",
      "source": "BusinessLine",
      "url": "https://www.thehindubusinessline.com/economy/india-us-chief-negotiators-to-hold-four-day-trade-talks-from-june-1/article71044288.ece",
      "published": "2026-05-31T09:56:17Z",
      "description": "The two sides are \"proposed to finalise the details of the interim agreement and take forward the negotiations under the broader BTA on multiple areas that includes market access, non-tariff measures,"
    },
    {
      "title": "New IIP series with FY23 base year to be out on Monday; credit-debit cards in, sewing machines out",
      "source": "BusinessLine",
      "url": "https://www.thehindubusinessline.com/economy/new-iip-series-with-fy23-base-year-to-be-out-on-monday-credit-debit-cards-in-sewing-machines-out/article71044128.ece",
      "published": "2026-05-31T09:32:11Z",
      "description": "The new series will have a base year of 2022-23, marking the 10th revision of the All India IIP, previously based on 2011-12"
    },
    {
      "title": "Will the base metals remain hot?",
      "source": "BusinessLine",
      "url": "https://www.thehindubusinessline.com/portfolio/will-the-base-metals-remain-hot/article71042294.ece",
      "published": "2026-05-30T15:51:39Z",
      "description": "Upside at risk. While supply disruptions can support rally, possible interest rate hikes later in the year can halt the same"
    },
    {
      "title": "当美妆品牌走进运动场：欧莱雅把校园公益做成了一场“运动实验”｜最前线",
      "source": "36kr.com",
      "url": "https://36kr.com/p/3831348302358408",
      "published": "2026-05-30T05:33:05Z",
      "description": "5月29日，欧莱雅中国在复旦大学启动2026年度“有意思青年”高校公益计划，并首次以校园运动会形式开启新一年的项目活动。活动现场，乒乓球运动员马龙、篮球运动员杨力维、足球运动员赵丽娜等体育界人士与高校学生展开互动，欧莱雅同时宣布向中国青少年发展基金会捐赠总价值约468万元的产品，并启动新一年度校园义卖活动。\n 从表面来看，这是一场校园公益活动；但放在全球美妆行业的发展背景下，它更像是美妆品牌持续拥"
    },
    {
      "title": "9点1氪｜泡泡玛特大涨，段永平日赚10亿；诺基亚发布首款微聊手机，售价199元；滴滴回应“乘客车内排泄”",
      "source": "36kr.com",
      "url": "https://36kr.com/p/3831073348855433",
      "published": "2026-05-30T00:52:20Z",
      "description": "今日热点导览\n <ul>\n <li>黄仁勋披露“赶飞机”细节，特朗普要出发时来电话</li>\n <li>国内航线燃油附加费6月5日起首次下调</li>\n <li>铁路将实施新规：违规乘车拒不补票将被限制购票</li>\n <li>iPhone 17系列中国销量破3000万台，Pro Max版占近一半</li>\n <li>SpaceX据悉将IPO估值目标下调至至少1.8万亿美元</li>\n </ul>"
    },
    {
      "title": "K92 Mining Announces Voting Results of Annual General Meeting of Shareholders",
      "source": "Financial Post",
      "url": "https://financialpost.com/globe-newswire/k92-mining-announces-voting-results-of-annual-general-meeting-of-shareholders-5",
      "published": "2026-05-29T21:41:02Z",
      "description": "VANCOUVER, British Columbia, May 29, 2026 (GLOBE NEWSWIRE) — K92 Mining Inc. (“K92” or the “Company”) (TSX: KNT; OTCQX: KNTNF) is pleased to announce the voting results of its 2026 annual general meet"
    },
    {
      "title": "K92 Mining Announces Election of Michael Carew to the Board of Directors",
      "source": "Financial Post",
      "url": "https://financialpost.com/globe-newswire/k92-mining-announces-election-of-michael-carew-to-the-board-of-directors",
      "published": "2026-05-29T19:54:15Z",
      "description": "VANCOUVER, British Columbia, May 29, 2026 (GLOBE NEWSWIRE) — K92 Mining Inc. (“K92” or the “Company”) (TSX: KNT; OTCQX: KNTNF) is pleased to announce that Michael Carew was elected to the Company’s Bo"
    }
  ],
  "tweets": []
}